{"algo-data-str_datastructure_linkedlist.md":"D4FRKOXd","article_record_td-cd.md":"fdoeafKM","algo-data-str_algorithm_mind.md":"DrgGR2cE","article_record_blog-refactor.md":"C_KzsY-R","article_record_dev-paradigm.md":"B9DfGaNr","article_record_nat.md":"nFAWkn87","article_record_qualified-engineer.md":"DH68I_Kd","algo-data-str_algorithm_sort.md":"DFGh5fTM","backend_devops_docker.md":"BgHTKtcW","article_record_webpack-vite.md":"BbjzI-Qs","algo-data-str_algorithm_dynamicplan.md":"rrBBVAta","article_record_js-prototype.md":"CHn7q0C8","article_record_vue-loader.md":"CIN90HJj","algo-data-str_complexity.md":"Db8P5YHR","article_record_td-custom.md":"B7xDIHE7","article_record_vca-refactor.md":"YwUrSC-A","algo-data-str_datastructure_tree.md":"Dave3CT2","algo-data-str_datastructure_index.md":"6XOKe_Z8","article_record_graphics-history.md":"BDN1ysUR","algo-data-str_index.md":"Bu0bvyKl","backend_db_mysql.md":"EjTvQ8iq","article_record_board.md":"8VUMKcIe","article_record_electron-updater.md":"D_89VrgT","backend_devops_ali-node.md":"BbiCdx1k","backend_db_redis.md":"Ch5cCuaq","algo-data-str_algorithm_doublepointer.md":"DutXacGJ","algo-data-str_algorithm_hash.md":"DTwdE4cR","font-end_engineering_webpack.md":"CL16AXOi","font-end_optimize_indicators.md":"DdUQKomg","font-end_js_event-loop.md":"D8jso4nh","font-end_engineering_npm.md":"BQeujIHr","backend_devops_linux.md":"ByTwCpAZ","basics_computer_threadsandprocesses.md":"BoIVXOaX","font-end-framework_react_article.md":"DeBoYaue","font-end_js_array.md":"CjqLxeud","algo-data-str_algorithm_backtrack.md":"BjY1Afwu","font-end-framework_react_redux.md":"Dscoli5J","algo-data-str_algorithm_math.md":"BJy8934_","font-end_js_typescript.md":"oglVOKi4","article_record_vitest-refactor.md":"DffomUqd","font-end_engineering_monitoring.md":"BNl_8BxO","font-end_engineering_optimize.md":"FaZ-3jYl","article_record_deploy.md":"DHGzHSSX","algo-data-str_algorithm_tree.md":"Deap68tu","work_tc-travel_siskin_import.md":"Bi2cDwEB","work_me.md":"DcrJKS36","work_tc-travel_business_growth.md":"CMjQiy5z","work_tc-travel_business_low-code.md":"B5Gn9b9I","work_tc-travel_index.md":"BoL5JOC5","graphics_render_webgl.md":"D50wLrgv","font-end_engineering_vite.md":"OAnnXvfR","index.md":"JaLcM2qE","work_ams_ads-system.md":"Bd0odLZ_","work_ams_noun-business.md":"m7Jj1P2d","graphics_math_linear-algebra.md":"D6yWLIzz","backend_devops_git-flow.md":"Cf3sRwGt","font-end-framework_vue_vue-protocol.md":"C33khB78","graphics_index.md":"Bfn2lao4","font-end_js_currying.md":"B133zp4X","work_tencent_2022.md":"D-8_3tfy","work_tc-travel_siskin_upload.md":"uFnNs8gj","font-end_browser_cross-domain.md":"DnP83Nc5","font-end_browser_security.md":"n25uJn2y","font-end_engineering_modular.md":"CSbIPg49","font-end-framework_architecture_event.md":"u3b89SLQ","backend_scene_currentlimiting.md":"CWQRv5bT","font-end-framework_index.md":"BjEPTqn9","font-end-framework_vue_vue3.md":"DpKVoSUG","basics_index.md":"9qPnuX_o","basics_network_connectionprocess.md":"BlrpiLOA","font-end_optimize_base.md":"WUwCGxMf","font-end_js_storage.md":"DMsNoKKg","graphics_engine_physics.md":"DqeDZWzc","font-end-framework_architecture_state.md":"ST2jT-G4","font-end_js_bom.md":"a25Bwpm8","graphics_engine_pixi.md":"p88qtWWb","graphics_engine_skia.md":"zSptgYPl","font-end_js_execute.md":"xkznzBkU","font-end_js_oom.md":"0WnlB5dF","font-end_js_string.md":"DpNv-G6C","font-end-framework_vue_ssr.md":"BPVNmxm7","basics_network_https.md":"af1BpMUJ","font-end_base_html.md":"k19d7hDl","basics_network_network-question.md":"DkJMI94S","font-end-framework_architecture_component.md":"LbXqSXq1","font-end-framework_architecture_diff.md":"Se7S4txK","font-end_js_utils.md":"B1T7stdh","font-end-framework_vue_reactive.md":"-4WXWwx6","font-end-framework_architecture_data.md":"bNpsAPMC","article_record_axure.md":"DIJ0wi0r","font-end_engineering_babel.md":"CcSYOlX1","algo-data-str_algorithm_linkedlist.md":"DCaYNIwM","font-end-framework_react_router.md":"7O_YLAxx","basics_math_linear-algebra.md":"C6jycp1r","basics_math_math-application.md":"CUC0Ymvi","basics_computer_howcomputerrun.md":"CiAccK-_","font-end_engineering_bridge.md":"DEmB7nAm","backend_index.md":"CC_OFsWp","font-end_browser_ajax.md":"DGv6h3DA","font-end_base_css.md":"UU10f-ne","font-end_browser_process.md":"Cc-yJx0n","basics_network_http.md":"Dvw5bCLg","font-end_index.md":"DvqAeB86","basics_thought_functional.md":"CGoZAonk","article_record_fe-monitor.md":"bahfdrFf","basics_network_cache.md":"DjcumLu2","backend_node_base.md":"Dsf4w0uU","article_index.md":"BoogmCP0","font-end-framework_react_question.md":"Bqr15XIc","backend_node_koa.md":"DIAT7eDC","basics_network_http-next.md":"BCR1GtTX","work_tc-travel_siskin_style.md":"DPEZI4rP","font-end-framework_architecture_logic-reuse.md":"soqXS2q2","work_tencent_2021.md":"BaCQG97N","work_tencent_2024.md":"P8gZR2kd","work_tencent_2023.md":"WhDAHb5x","graphics_render_canvas.md":"DNiIXxu9","basics_network_http-code.md":"aUlrr3Ny","graphics_render_svg.md":"DuLya_6c","font-end_base_bem.md":"DTboC1rM","font-end_base_mobile-adapter.md":"CyV6-r6g","font-end_browser_auth.md":"BUMkVvja","work_tc-travel_siskin_unit-test.md":"BOoaKHEz","font-end-framework_architecture_compile.md":"BaYAYcYT","font-end_js_scope-gc.md":"Xycr0pFd","font-end-framework_vue_vuex.md":"CSA_hVTo","font-end-framework_vue_question.md":"_MKwqIBC","font-end-framework_react_core.md":"CW9sloZ_","font-end-framework_vue_router.md":"qAtrQsBi","basics_thought_design-mode.md":"Fdk-DJN6","font-end_engineering_evolution.md":"aeB-O4Sa","font-end-framework_architecture_render.md":"COSnvi6Q","algo-data-str_algorithm_stack.md":"CIxA5RGK","font-end_base_load.md":"CqqMaTHK","backend_devops_nginx.md":"DhlpQUKJ","font-end_browser_base.md":"d7V1Qyei","font-end-framework_mini-program_index.md":"By-os2jR","font-end_optimize_engineering.md":"Cf7rnEac","font-end-framework_architecture_lifecycle.md":"DlR1YoGc","font-end-framework_vue_core.md":"C3R6LN72","algo-data-str_algorithm_binarysearch.md":"B0VU_kIB"}
